mozci/__init__.py
mozci/configuration.py
mozci/console/application.py
mozci/console/commands/batch_execution.py
mozci/console/commands/build_regression.py
mozci/console/commands/check_backfills.py
mozci/console/commands/decision.py
mozci/console/commands/push.py
mozci/data/__init__.py
mozci/data/base.py
mozci/data/contract.py
mozci/data/sources/__init__.py
mozci/data/sources/artifact/__init__.py
mozci/data/sources/bugbug/__init__.py
mozci/data/sources/hgmo/__init__.py
mozci/data/sources/taskcluster/__init__.py
mozci/data/sources/treeherder/__init__.py
mozci/errors.py
mozci/push.py
mozci/task.py
mozci/util/__init__.py
mozci/util/cache_stores.py
mozci/util/defs.py
mozci/util/hgmo.py
mozci/util/logging.py
mozci/util/memoize.py
mozci/util/req.py
mozci/util/taskcluster.py
mozci/util/yaml.py
mozci-2.4.3.dist-info/LICENSE
mozci-2.4.3.dist-info/METADATA
mozci-2.4.3.dist-info/WHEEL
mozci-2.4.3.dist-info/entry_points.txt
mozci-2.4.3.dist-info/RECORD
